LICENSE
MANIFEST.in
README.md
setup.cfg
setup.py
chowkidar/__init__.py
chowkidar/admin.py
chowkidar/models.py
chowkidar/settings.py
chowkidar/tests.py
chowkidar/auth/__init__.py
chowkidar/auth/authenticate.py
chowkidar/auth/fingerprint.py
chowkidar/auth/handler.py
chowkidar/auth/middleware.py
chowkidar/auth/rules.py
chowkidar/auth/verify.py
chowkidar/graphql/__init__.py
chowkidar/graphql/channel.py
chowkidar/graphql/decorators.py
chowkidar/graphql/exceptions.py
chowkidar/graphql/files.py
chowkidar/graphql/scalars.py
chowkidar/graphql/schema.py
chowkidar/graphql/view.py
chowkidar/migrations/0001_initial.py
chowkidar/migrations/0002_auto_20210111_1922.py
chowkidar/migrations/__init__.py
chowkidar/templates/graphiql/graphiql.html
chowkidar/utils/__init__.py
chowkidar/utils/cookie.py
chowkidar/utils/exceptions.py
chowkidar/utils/jwt.py
chowkidar/utils/refresh_token.py
chowkidar/utils/settings.py
chowkidar_graphene.egg-info/PKG-INFO
chowkidar_graphene.egg-info/SOURCES.txt
chowkidar_graphene.egg-info/dependency_links.txt
chowkidar_graphene.egg-info/not-zip-safe
chowkidar_graphene.egg-info/top_level.txt