Metadata-Version: 2.1
Name: chowkidar-graphene
Version: 0.7.0
Summary: All-in-One JWT Authentication plugin for Graphene
Home-page: https://github.com/aswinshenoy/chowkidar
Author: Ashwin Shenoy
Author-email: aswinshenoy65@gmail.com
Maintainer: Ashwin Shenoy
Maintainer-email: aswinshenoy65@gmail.com
License: GNU-GPL-V3
Platform: UNKNOWN
Classifier: Environment :: Web Environment
Classifier: Intended Audience :: Developers
Classifier: Development Status :: 4 - Beta
Classifier: License :: OSI Approved :: GNU General Public License v3 (GPLv3)
Classifier: Operating System :: OS Independent
Classifier: Programming Language :: Python
Classifier: Programming Language :: Python :: 3
Classifier: Programming Language :: Python :: 3.4
Classifier: Programming Language :: Python :: 3.5
Classifier: Programming Language :: Python :: 3.6
Classifier: Programming Language :: Python :: 3.7
Classifier: Programming Language :: Python :: 3.8
Classifier: Framework :: Django
Classifier: Framework :: Django :: 2.2
Classifier: Framework :: Django :: 3.0
